descanso/__init__.py
descanso/_version.py
descanso/bound_method.py
descanso/builder_base.py
descanso/client.py
descanso/exceptions.py
descanso/jsonrpc.py
descanso/method_descriptor.py
descanso/method_spec.py
descanso/py.typed
descanso/request.py
descanso/request_transformers.py
descanso/response.py
descanso/response_transformers.py
descanso/rest_builder.py
descanso/signature.py
descanso/utils.py
descanso/http/__init__.py
descanso/http/aiohttp.py
descanso/http/httpx.py
descanso/http/requests.py
descanso-0.7.1.dist-info/licenses/LICENSE
descanso-0.7.1.dist-info/METADATA
descanso-0.7.1.dist-info/WHEEL
descanso-0.7.1.dist-info/top_level.txt
descanso-0.7.1.dist-info/RECORD
