Metadata-Version: 2.4
Name: descanso
Version: 0.7.1
Summary: A client framework for HTTP APIs
Author-email: Andrey Tikhonov <17@itishka.org>
License-Expression: Apache-2.0
Project-URL: Source, https://github.com/reagento/descanso
Project-URL: Homepage, https://github.com/reagento/descanso
Project-URL: Documentation, https://descanso.readthedocs.io/en/stable/
Project-URL: Bug Tracker, https://github.com/reagento/descanso/issues
Classifier: Programming Language :: Python :: 3.10
Classifier: Programming Language :: Python :: 3.11
Classifier: Programming Language :: Python :: 3.12
Classifier: Programming Language :: Python :: 3.13
Classifier: Programming Language :: Python :: 3.14
Classifier: Topic :: Software Development :: Libraries
Classifier: Typing :: Typed
Classifier: Intended Audience :: Developers
Classifier: Operating System :: OS Independent
Requires-Python: >=3.10
License-File: LICENSE
Requires-Dist: kiss-headers
Dynamic: license-file
